nonebot_plugin_mahjong_scoreboard/__init__.py
nonebot_plugin_mahjong_scoreboard/config.py
nonebot_plugin_mahjong_scoreboard/controller/__init__.py
nonebot_plugin_mahjong_scoreboard/controller/game_export.py
nonebot_plugin_mahjong_scoreboard/controller/game_query.py
nonebot_plugin_mahjong_scoreboard/controller/game_record.py
nonebot_plugin_mahjong_scoreboard/controller/game_statistics.py
nonebot_plugin_mahjong_scoreboard/controller/interceptor/__init__.py
nonebot_plugin_mahjong_scoreboard/controller/mapper/__init__.py
nonebot_plugin_mahjong_scoreboard/controller/mapper/game_csv_mapper.py
nonebot_plugin_mahjong_scoreboard/controller/mapper/game_mapper.py
nonebot_plugin_mahjong_scoreboard/controller/mapper/pagination_mapper.py
nonebot_plugin_mahjong_scoreboard/controller/mapper/season_mapper.py
nonebot_plugin_mahjong_scoreboard/controller/mapper/season_user_point_csv_mapper.py
nonebot_plugin_mahjong_scoreboard/controller/mapper/season_user_point_mapper.py
nonebot_plugin_mahjong_scoreboard/controller/mg.py
nonebot_plugin_mahjong_scoreboard/controller/season_manage.py
nonebot_plugin_mahjong_scoreboard/controller/season_query.py
nonebot_plugin_mahjong_scoreboard/controller/season_user_point_export.py
nonebot_plugin_mahjong_scoreboard/controller/season_user_point_manage.py
nonebot_plugin_mahjong_scoreboard/controller/season_user_point_query.py
nonebot_plugin_mahjong_scoreboard/controller/templates/style.css
nonebot_plugin_mahjong_scoreboard/controller/templates/table.html
nonebot_plugin_mahjong_scoreboard/controller/utils/__init__.py
nonebot_plugin_mahjong_scoreboard/controller/utils/dep.py
nonebot_plugin_mahjong_scoreboard/controller/utils/general_handlers.py
nonebot_plugin_mahjong_scoreboard/controller/utils/message.py
nonebot_plugin_mahjong_scoreboard/controller/utils/parse.py
nonebot_plugin_mahjong_scoreboard/controller/utils/send_csv.py
nonebot_plugin_mahjong_scoreboard/controller/utils/send_msg.py
nonebot_plugin_mahjong_scoreboard/errors.py
nonebot_plugin_mahjong_scoreboard-0.7.0.dist-info/LICENSE
nonebot_plugin_mahjong_scoreboard-0.7.0.dist-info/METADATA
nonebot_plugin_mahjong_scoreboard-0.7.0.dist-info/WHEEL
nonebot_plugin_mahjong_scoreboard-0.7.0.dist-info/RECORD
