Metadata-Version: 2.1
Name: nonebot-plugin-mahjong-scoreboard
Version: 0.7.0
Summary: 日麻寄分器（NoneBot插件）
Home-page: https://github.com/ssttkkl/nonebot-plugin-mahjong-scoreboard
License: MIT
Author: ssttkkl
Author-email: huang.wen.long@hotmail.com
Requires-Python: >=3.9,<4.0
Classifier: License :: OSI Approved :: MIT License
Classifier: Programming Language :: Python :: 3
Classifier: Programming Language :: Python :: 3.9
Classifier: Programming Language :: Python :: 3.10
Classifier: Programming Language :: Python :: 3.11
Classifier: Programming Language :: Python :: 3.12
Classifier: Programming Language :: Python :: 3.13
Provides-Extra: htmlrender
Requires-Dist: aiosqlite (>=0.17.0)
Requires-Dist: cachetools (>=5.2.0)
Requires-Dist: nonebot-plugin-gocqhttp-cross-machine-upload-file (>=0.1.5)
Requires-Dist: nonebot-plugin-htmlrender (>=0.2.0.3) ; extra == "htmlrender"
Requires-Dist: nonebot-plugin-localstore (>=0.5.1)
Requires-Dist: nonebot-plugin-send-anything-anywhere (>=0.3.0) ; extra == "htmlrender"
Requires-Dist: nonebot-plugin-session (>=0.2.0)
Requires-Dist: nonebot-plugin-sqlalchemy (>=0.2.1)
Requires-Dist: nonebot2 (>=2.2,<3.0)
Requires-Dist: nonebot_plugin_apscheduler (>=0.3.0)
Requires-Dist: prettytable (>=3.8.0) ; extra == "htmlrender"
Requires-Dist: ssttkkl-nonebot-utils (>=0.1.15)
Requires-Dist: tzlocal (>=4.2)
Project-URL: Repository, https://github.com/ssttkkl/nonebot-plugin-mahjong-scoreboard
